previsedx_esopredict_qc_utils/__init__.py
previsedx_esopredict_qc_utils/console_helper.py
previsedx_esopredict_qc_utils/constants.py
previsedx_esopredict_qc_utils/file_utils.py
previsedx_esopredict_qc_utils/run_esopredict_qc_checks.py
previsedx_esopredict_qc_utils/system_caller.py
previsedx_esopredict_qc_utils/conf/config.yaml
previsedx_esopredict_qc_utils/esopredict/__init__.py
previsedx_esopredict_qc_utils/esopredict/analysis/__init__.py
previsedx_esopredict_qc_utils/esopredict/analysis/results/__init__.py
previsedx_esopredict_qc_utils/esopredict/analysis/results/final_record.py
previsedx_esopredict_qc_utils/esopredict/analysis/results/file/__init__.py
previsedx_esopredict_qc_utils/esopredict/analysis/results/file/dataset.py
previsedx_esopredict_qc_utils/esopredict/analysis/results/file/file.py
previsedx_esopredict_qc_utils/esopredict/analysis/results/file/helper.py
previsedx_esopredict_qc_utils/esopredict/analysis/results/file/record.py
previsedx_esopredict_qc_utils/esopredict/analysis/results/file/xlsx/__init__.py
previsedx_esopredict_qc_utils/esopredict/analysis/results/file/xlsx/parser.py
previsedx_esopredict_qc_utils/esopredict/analysis/results/intermediate/__init__.py
previsedx_esopredict_qc_utils/esopredict/analysis/results/intermediate/file/__init__.py
previsedx_esopredict_qc_utils/esopredict/analysis/results/intermediate/file/tsv/__init__.py
previsedx_esopredict_qc_utils/esopredict/analysis/results/intermediate/file/tsv/parser.py
previsedx_esopredict_qc_utils/qc/__init__.py
previsedx_esopredict_qc_utils/qc/auditor.py
previsedx_esopredict_qc_utils/qc/manager.py
previsedx_esopredict_qc_utils/qc/record.py
previsedx_esopredict_qc_utils/qc/reporter.py
previsedx_esopredict_qc_utils-0.5.0.dist-info/AUTHORS.rst
previsedx_esopredict_qc_utils-0.5.0.dist-info/METADATA
previsedx_esopredict_qc_utils-0.5.0.dist-info/WHEEL
previsedx_esopredict_qc_utils-0.5.0.dist-info/entry_points.txt
previsedx_esopredict_qc_utils-0.5.0.dist-info/top_level.txt
previsedx_esopredict_qc_utils-0.5.0.dist-info/RECORD
