Metadata-Version: 2.1
Name: previsedx-esopredict-qc-utils
Version: 0.5.0
Summary: Collection of software for QC checks for PreviseDx Esopredict.
Home-page: https://github.com/sundaram-previsedx/previsedx-esopredict-qc-utils
Author: Jaideep Sundaram
Author-email: sundaram.previse@gmail.com
License: UNKNOWN
Keywords: previsedx_esopredict_qc_utils
Platform: UNKNOWN
Classifier: Development Status :: 2 - Pre-Alpha
Classifier: Intended Audience :: Developers
Classifier: Natural Language :: English
Classifier: Programming Language :: Python :: 3
Classifier: Programming Language :: Python :: 3.6
Classifier: Programming Language :: Python :: 3.7
Classifier: Programming Language :: Python :: 3.8
Requires-Python: >=3.6
License-File: AUTHORS.rst
Requires-Dist: Click>=7.0
Requires-Dist: PyYAML
Requires-Dist: Rich
Requires-Dist: pandas
Requires-Dist: pydantic
Requires-Dist: xlrd>=2.0.1
